cookiecutter_python_cli_app_demo/__init__.py
cookiecutter_python_cli_app_demo/__main__.py
cookiecutter_python_cli_app_demo/cli.py
cookiecutter_python_cli_app_demo/py.typed
cookiecutter_python_cli_app_demo-2025.1.0.dist-info/WHEEL
cookiecutter_python_cli_app_demo-2025.1.0.dist-info/entry_points.txt
cookiecutter_python_cli_app_demo-2025.1.0.dist-info/METADATA
cookiecutter_python_cli_app_demo-2025.1.0.dist-info/RECORD
