Metadata-Version: 2.3
Name: cookiecutter-python-cli-app-demo
Version: 2025.1.0
Summary: Demo of https://github.com/sgraaf/cookiecutter-python-cli-app.
Keywords: 
Author: Steven van de Graaf
Author-email: Steven van de Graaf <steven@vandegraaf.xyz>
License: MIT License
Classifier: Development Status :: 4 - Beta
Classifier: Environment :: Console
Classifier: Intended Audience :: Developers
Classifier: License :: OSI Approved :: MIT License
Classifier: Programming Language :: Python
Classifier: Programming Language :: Python :: 3
Classifier: Programming Language :: Python :: 3.9
Classifier: Programming Language :: Python :: 3.10
Classifier: Programming Language :: Python :: 3.11
Classifier: Programming Language :: Python :: 3.12
Classifier: Programming Language :: Python :: 3.13
Classifier: Programming Language :: Python :: 3 :: Only
Classifier: Typing :: Typed
Requires-Dist: click
Requires-Python: ~=3.9
Project-URL: Changelog, https://cookiecutter-python-cli-app-demo.readthedocs.io/en/stable/changelog.html
Project-URL: Documentation, https://cookiecutter-python-cli-app-demo.readthedocs.io/en/stable/
Project-URL: Issue Tracker, https://github.com/sgraaf/cookiecutter-python-cli-app-demo/issues
Project-URL: Source Code, https://github.com/sgraaf/cookiecutter-python-cli-app-demo
